bayesian_filters/__init__.py
bayesian_filters/changelog.txt
bayesian_filters/common/__init__.py
bayesian_filters/common/discretization.py
bayesian_filters/common/helpers.py
bayesian_filters/common/kinematic.py
bayesian_filters/common/tests/test_discretization.py
bayesian_filters/common/tests/test_helpers.py
bayesian_filters/discrete_bayes/__init__.py
bayesian_filters/discrete_bayes/discrete_bayes.py
bayesian_filters/discrete_bayes/tests/test_discrete_bayes.py
bayesian_filters/examples/GetRadar.py
bayesian_filters/examples/README.md
bayesian_filters/examples/RadarUKF.py
bayesian_filters/examples/__init__.py
bayesian_filters/examples/bearing_only.py
bayesian_filters/examples/radar_sim.py
bayesian_filters/gh/__init__.py
bayesian_filters/gh/gh_filter.py
bayesian_filters/gh/tests/test_gh.py
bayesian_filters/hinfinity/__init__.py
bayesian_filters/hinfinity/hinfinity_filter.py
bayesian_filters/hinfinity/tests/test_hinfinity.py
bayesian_filters/kalman/.gitignore
bayesian_filters/kalman/CubatureKalmanFilter.py
bayesian_filters/kalman/EKF.py
bayesian_filters/kalman/IMM.py
bayesian_filters/kalman/UKF.py
bayesian_filters/kalman/__init__.py
bayesian_filters/kalman/ensemble_kalman_filter.py
bayesian_filters/kalman/fading_memory.py
bayesian_filters/kalman/fixed_lag_smoother.py
bayesian_filters/kalman/information_filter.py
bayesian_filters/kalman/kalman_filter.py
bayesian_filters/kalman/mmae.py
bayesian_filters/kalman/sigma_points.py
bayesian_filters/kalman/square_root.py
bayesian_filters/kalman/unscented_transform.py
bayesian_filters/kalman/tests/test_ckf.py
bayesian_filters/kalman/tests/test_ekf.py
bayesian_filters/kalman/tests/test_enkf.py
bayesian_filters/kalman/tests/test_fls.py
bayesian_filters/kalman/tests/test_fm.py
bayesian_filters/kalman/tests/test_imm.py
bayesian_filters/kalman/tests/test_information.py
bayesian_filters/kalman/tests/test_kf.py
bayesian_filters/kalman/tests/test_mmae.py
bayesian_filters/kalman/tests/test_rts.py
bayesian_filters-1.4.5.dist-info/METADATA
bayesian_filters-1.4.5.dist-info/WHEEL
bayesian_filters-1.4.5.dist-info/licenses/LICENSE
bayesian_filters-1.4.5.dist-info/RECORD
