Metadata-Version: 2.4
Name: bayesian-filters
Version: 1.4.5
Summary: Kalman filtering and optimal estimation library
Project-URL: Homepage, https://github.com/GeorgePearse/bayesian_filters
Project-URL: Repository, https://github.com/GeorgePearse/bayesian_filters
Project-URL: Documentation, https://georgepearse.github.io/bayesian_filters
Project-URL: Original Project, https://github.com/rlabbe/filterpy
Author-email: Roger Labbe <rlabbejr@gmail.com>
License: MIT
License-File: LICENSE
Keywords: Bayesian,Kalman,estimation,filtering,filters,optimal,tracking
Classifier: Development Status :: 5 - Production/Stable
Classifier: Intended Audience :: Developers
Classifier: Intended Audience :: Education
Classifier: Intended Audience :: Science/Research
Classifier: License :: OSI Approved :: MIT License
Classifier: Operating System :: MacOS
Classifier: Operating System :: Microsoft :: Windows
Classifier: Operating System :: POSIX
Classifier: Operating System :: Unix
Classifier: Programming Language :: Python :: 3
Classifier: Programming Language :: Python :: 3.9
Classifier: Programming Language :: Python :: 3.10
Classifier: Programming Language :: Python :: 3.11
Classifier: Programming Language :: Python :: 3.12
Classifier: Topic :: Scientific/Engineering
Classifier: Topic :: Scientific/Engineering :: Mathematics
Classifier: Topic :: Scientific/Engineering :: Physics
Classifier: Topic :: Utilities
Requires-Python: >=3.9
Requires-Dist: matplotlib
Requires-Dist: numpy
Requires-Dist: scipy
Provides-Extra: dev
Requires-Dist: pytest-cov>=4.0.0; extra == 'dev'
Requires-Dist: pytest>=8.0.0; extra == 'dev'
Provides-Extra: docs
Requires-Dist: mkdocs-material>=9.0.0; extra == 'docs'
Requires-Dist: mkdocs>=1.5.0; extra == 'docs'
Requires-Dist: mkdocstrings[python]>=0.24.0; extra == 'docs'
